adabelief_pytorch/AdaBelief.py
adabelief_pytorch/__init__.py
adabelief_pytorch-0.2.1.dist-info/LICENSE.txt
adabelief_pytorch-0.2.1.dist-info/METADATA
adabelief_pytorch-0.2.1.dist-info/WHEEL
adabelief_pytorch-0.2.1.dist-info/top_level.txt
adabelief_pytorch-0.2.1.dist-info/RECORD
