Metadata-Version: 2.1
Name: adabelief_pytorch
Version: 0.2.1
Summary: PyTorch implementation of AdaBelief Optimizer
Home-page: https://juntang-zhuang.github.io/adabelief/
Author: Juntang Zhuang
Author-email: j.zhuang@yale.edu
License: UNKNOWN
Platform: UNKNOWN
Classifier: Programming Language :: Python :: 3
Classifier: License :: OSI Approved :: MIT License
Classifier: Operating System :: OS Independent
Requires-Python: >=3.6
